{
  "name": "mongodb-connector",
  "config": {
    "connector.class": "io.debezium.connector.mongodb.MongoDbConnector",
    "tasks.max": "1",
    "mongodb.connection.string": "mongodb://admin:root@mongodb:27017/test?replicaSet=rs0&authSource=admin",
    "database.include.list": "test",
    "collection.include.list": "test.books",
    "topic.prefix": "mongodb_server",
    "key.converter": "org.apache.kafka.connect.json.JsonConverter",
    "value.converter": "org.apache.kafka.connect.json.JsonConverter",
    "key.converter.schemas.enable": "false",
    "value.converter.schemas.enable": "false",
    "transforms": "unwrap",
    "transforms.unwrap.type": "io.debezium.transforms.ExtractNewRecordState",
    "transforms.unwrap.drop.tombstones": "false",
    "transforms.unwrap.delete.handling.mode": "rewrite",
    "transforms.unwrap.add.fields": "op"
  }
}

